{
  "1": "YUNI ASTUTI, S.Pd",
  "2": "SRI RAHAYU, S.Pd",
  "3": "SUWARNI, S.Pd",
  "4": "SITI ROMLAH, S.Pd",
  "5": "SUKARIYEM, S.Pd",
  "6": "MARLIYAH, S.Pd",
  "7": "DENY KARTIKA SAKTI, S.Pd",
  "8": "MARIA ULFAH, S.Pd",
  "9": "SULISTIANI, S.Pd",
  "10": "LIA RAHMAWATI, S.Pd",
  "11": "KHUSNUL LAILI, S.Ag",
  "12": "RUDI SUGENG HARIYADI, S.Pd",
  "13": "YENI SUSANTI, S.Pd",
  "14": "BERNADUS ANANDRA EGATRI, S.Pd",
  "15": "TITIK FITRIATUSSAIDAH, S.Pd",
  "16": "DIYAH SUKORENANINGTYAS, S.Pd",
  "17": "DWI INDRAWATI, S.Pd",
  "18": "UBAIDILLAH, S.Pd",
  "19": "KHUSNUL SULISTIYANI, S.Pd",
  "20": "ILHAM MA'ARIF, S.Pd",
  "21": "SEMIATI, S.Pd",
  "22": "NUR HASANAH, S.Pd",
  "23": "SUGIONO, S.Pd",
  "24": "EKO KRISTINA RAHAYU, S.Sn",
  "25": "RANI MANGISTUTI, S.Pd",
  "26": "SHOLIHHATY FITRIYAH, S.Pd",
  "27": "PUTRI MEGA KARTIKA SARI, S.Pd",
  "28": "LATIFATUL ILMIYAH, S.Pd",
  "29": "DIYAH AGUS SETYOWATI, S.Pd",
  "30": "MOHAMMAD NASHIR, S.Pd",
  "31": "HIDAYAH BUDIARINI, S.Pd",
  "32": "AFI KHUSAMUDDIN, S.Pd",
  "33": "IRKHAM MAULANA MARZUKI, S.Pd",
  "34": "NUR KHUSAINI, S.Pd",
  "35": "ILHAM WIDYA YUDA, S.Pd",
  "36": "ANEKE FRANSISKA KURNIA, S.Pd",
  "37": "MUCHAMAD ALI FIKRI, S.Kom",
  "38": "DODI FEBRIANSYAH, S.Kom",
  "39": "MUHAMAD SYAIFUDIN, S.Pd",
  "40": "ILMA NURFIATISSOLICHAH, S.Pd",
  "41": "NURJIHAN ABIDATUR ROFIFAH, S.Pd",
  "42": "SHEILA ADETIA, S.Pd",
  "43": "RISDA MAULIDA NINGTIYAS, S.Pd",
  "44": "ALIF RAHMAT MAULANA, S.Ag",
  "45": "SITI KHOLIFAH, S.Pd",
  "46": "THORIQ ABDUL AZIZ, S.Pd",
  "47": "ACHMAD ROSA FATHONI, S.A.Md",
  "48": "NURUL MAGHFIROH, S.E",
  "49": "LAILI MASRUROH"
}
